servicecatalogtordf/__init__.py
servicecatalogtordf/criterion_requirement.py
servicecatalogtordf/event.py
servicecatalogtordf/evidence.py
servicecatalogtordf/legal_resource.py
servicecatalogtordf/public_organization.py
servicecatalogtordf/rule.py
servicecatalogtordf/service.py
servicecatalogtordf-0.1.0a15.dist-info/LICENSE
servicecatalogtordf-0.1.0a15.dist-info/WHEEL
servicecatalogtordf-0.1.0a15.dist-info/METADATA
servicecatalogtordf-0.1.0a15.dist-info/RECORD
