Metadata-Version: 2.1
Name: servicecatalogtordf
Version: 0.1.0a15
Summary: A library that will map a service catalog (cpsv) to rdf
Home-page: https://github.com/Informasjonsforvaltning/servicecatalogtordf
License: Apache-2.0
Author: Stig B. Dørmænen
Author-email: stigbd@gmail.com
Requires-Python: >=3.8,<3.10
Classifier: License :: OSI Approved :: Apache Software License
Classifier: Operating System :: OS Independent
Classifier: Programming Language :: Python :: 3
Classifier: Programming Language :: Python :: 3.8
Classifier: Programming Language :: Python :: 3.9
Requires-Dist: datacatalogtordf (>=1.5.1,<2.0.0)
Requires-Dist: skolemizer (>=1.1.0,<2.0.0)
Project-URL: Documentation, https://servicecatalogtordf.readthedocs.io
Project-URL: Repository, https://github.com/Informasjonsforvaltning/servicecatalogtordf
